<annotation>
		<size>
			<width>640</width>
			<height>512</height>
			<depth>3</depth>
		</size>
		<segmented>0</segmented>
		<object>
			<name>person</name>
			<pose>Unspecified</pose>
			<truncated>0</truncated>
			<point>
				<x>476</x>
				<y>184</y>
			</point>
		</object>
		<object>
			<name>person</name>
			<pose>Unspecified</pose>
			<truncated>0</truncated>
			<point>
				<x>467</x>
				<y>181</y>
			</point>
		</object>
		<object>
			<name>person</name>
			<pose>Unspecified</pose>
			<truncated>0</truncated>
			<point>
				<x>492</x>
				<y>177</y>
			</point>
		</object>
		<object>
			<name>person</name>
			<pose>Unspecified</pose>
			<truncated>0</truncated>
			<point>
				<x>517</x>
				<y>171</y>
			</point>
		</object>
		<object>
			<name>person</name>
			<pose>Unspecified</pose>
			<truncated>0</truncated>
			<point>
				<x>544</x>
				<y>178</y>
			</point>
		</object>
		<object>
			<name>person</name>
			<pose>Unspecified</pose>
			<truncated>0</truncated>
			<point>
				<x>534</x>
				<y>187</y>
			</point>
		</object>
		<object>
			<name>person</name>
			<pose>Unspecified</pose>
			<truncated>0</truncated>
			<point>
				<x>577</x>
				<y>234</y>
			</point>
		</object>
		<object>
			<name>person</name>
			<pose>Unspecified</pose>
			<truncated>0</truncated>
			<point>
				<x>580</x>
				<y>219</y>
			</point>
		</object>
		<object>
			<name>person</name>
			<pose>Unspecified</pose>
			<truncated>0</truncated>
			<point>
				<x>477</x>
				<y>217</y>
			</point>
		</object>
		<object>
			<name>person</name>
			<pose>Unspecified</pose>
			<truncated>0</truncated>
			<point>
				<x>469</x>
				<y>216</y>
			</point>
		</object>
		<object>
			<name>person</name>
			<pose>Unspecified</pose>
			<truncated>0</truncated>
			<point>
				<x>365</x>
				<y>216</y>
			</point>
		</object>
		<object>
			<name>person</name>
			<pose>Unspecified</pose>
			<truncated>0</truncated>
			<point>
				<x>396</x>
				<y>171</y>
			</point>
		</object>
		<object>
			<name>person</name>
			<pose>Unspecified</pose>
			<truncated>0</truncated>
			<point>
				<x>399</x>
				<y>178</y>
			</point>
		</object>
		<object>
			<name>person</name>
			<pose>Unspecified</pose>
			<truncated>0</truncated>
			<point>
				<x>190</x>
				<y>208</y>
			</point>
		</object>
		<object>
			<name>person</name>
			<pose>Unspecified</pose>
			<truncated>0</truncated>
			<point>
				<x>181</x>
				<y>210</y>
			</point>
		</object>
		<object>
			<name>person</name>
			<pose>Unspecified</pose>
			<truncated>0</truncated>
			<point>
				<x>139</x>
				<y>428</y>
			</point>
		</object>
		<object>
			<name>person</name>
			<pose>Unspecified</pose>
			<truncated>0</truncated>
			<point>
				<x>287</x>
				<y>457</y>
			</point>
		</object>
		<object>
			<name>person</name>
			<pose>Unspecified</pose>
			<truncated>0</truncated>
			<point>
				<x>284</x>
				<y>464</y>
			</point>
		</object>
		<object>
			<name>person</name>
			<pose>Unspecified</pose>
			<truncated>0</truncated>
			<point>
				<x>356</x>
				<y>489</y>
			</point>
		</object>
		<object>
			<name>person</name>
			<pose>Unspecified</pose>
			<truncated>0</truncated>
			<point>
				<x>399</x>
				<y>402</y>
			</point>
		</object>
		<object>
			<name>person</name>
			<pose>Unspecified</pose>
			<truncated>0</truncated>
			<point>
				<x>399</x>
				<y>416</y>
			</point>
		</object>
		<object>
			<name>person</name>
			<pose>Unspecified</pose>
			<truncated>0</truncated>
			<point>
				<x>423</x>
				<y>467</y>
			</point>
		</object>
		<object>
			<name>person</name>
			<pose>Unspecified</pose>
			<truncated>0</truncated>
			<point>
				<x>532</x>
				<y>417</y>
			</point>
		</object>
		<object>
			<name>person</name>
			<pose>Unspecified</pose>
			<truncated>0</truncated>
			<point>
				<x>522</x>
				<y>411</y>
			</point>
		</object>
		<object>
			<name>person</name>
			<pose>Unspecified</pose>
			<truncated>0</truncated>
			<point>
				<x>585</x>
				<y>423</y>
			</point>
		</object>
		<object>
			<name>person</name>
			<pose>Unspecified</pose>
			<truncated>0</truncated>
			<point>
				<x>597</x>
				<y>475</y>
			</point>
		</object>
		<object>
			<name>person</name>
			<pose>Unspecified</pose>
			<truncated>0</truncated>
			<point>
				<x>610</x>
				<y>422</y>
			</point>
		</object>
		<object>
			<name>person</name>
			<pose>Unspecified</pose>
			<truncated>0</truncated>
			<point>
				<x>601</x>
				<y>414</y>
			</point>
		</object>
		<object>
			<name>person</name>
			<pose>Unspecified</pose>
			<truncated>0</truncated>
			<point>
				<x>605</x>
				<y>422</y>
			</point>
		</object>
	</annotation>